beancount_commerzbank/__init__.py
beancount_commerzbank/ec.py
beancount_commerzbank-0.2.1.dist-info/LICENSE.txt
beancount_commerzbank-0.2.1.dist-info/WHEEL
beancount_commerzbank-0.2.1.dist-info/METADATA
beancount_commerzbank-0.2.1.dist-info/RECORD
