Metadata-Version: 2.1
Name: beancount-commerzbank
Version: 0.2.1
Summary: Beancount Importer for Commerzbank (DE) CSV exports
Home-page: https://github.com/siddhantgoel/beancount-commerzbank
License: MIT
Keywords: beancount,cli-accounting,finance
Author: Siddhant Goel
Author-email: me@sgoel.org
Requires-Python: >=3.5,<4.0
Classifier: Development Status :: 4 - Beta
Classifier: Environment :: Plugins
Classifier: Intended Audience :: End Users/Desktop
Classifier: Intended Audience :: Financial and Insurance Industry
Classifier: License :: OSI Approved :: MIT License
Classifier: Programming Language :: Python :: 3
Classifier: Programming Language :: Python :: 3 :: Only
Classifier: Programming Language :: Python :: 3.5
Classifier: Programming Language :: Python :: 3.6
Classifier: Programming Language :: Python :: 3.7
Project-URL: Repository, https://github.com/siddhantgoel/beancount-commerzbank
